inferno/.gitignore
inferno/__init__.py
inferno/_version.py
inferno/bnn/__init__.py
inferno/bnn/temperature_scaler.py
inferno/bnn/modules/__init__.py
inferno/bnn/modules/attention.py
inferno/bnn/modules/bnn_mixin.py
inferno/bnn/modules/conv.py
inferno/bnn/modules/linear.py
inferno/bnn/modules/sin_pos_encoding.py
inferno/bnn/modules/containers/__init__.py
inferno/bnn/modules/containers/sequential.py
inferno/bnn/params/__init__.py
inferno/bnn/params/gaussian_parameter.py
inferno/bnn/params/parameter.py
inferno/bnn/params/covariances/__init__.py
inferno/bnn/params/covariances/diagonal.py
inferno/bnn/params/covariances/factorized.py
inferno/bnn/params/covariances/kronecker.py
inferno/bnn/params/covariances/low_rank.py
inferno/bnn/params/parametrizations/__init__.py
inferno/bnn/params/parametrizations/maximal_update.py
inferno/bnn/params/parametrizations/neural_tangent.py
inferno/bnn/params/parametrizations/parametrization.py
inferno/bnn/params/parametrizations/standard.py
inferno/datasets/__init__.py
inferno/datasets/regression_dataset.py
inferno/datasets/image/__init__.py
inferno/datasets/image/cifar.py
inferno/datasets/image/fashion_mnist.py
inferno/datasets/image/mnist.py
inferno/datasets/image/tiny_imagenet.py
inferno/datasets/tabular/__init__.py
inferno/datasets/tabular/concrete_compressive_strength.py
inferno/datasets/tabular/parkinsons_telemonitoring.py
inferno/datasets/tabular/protein_structure.py
inferno/datasets/tabular/road_network.py
inferno/datasets/tabular/wine_quality.py
inferno/datasets/text/__init__.py
inferno/loss_fns/__init__.py
inferno/loss_fns/focal_loss.py
inferno/loss_fns/variance_reduced_loss_fns.py
inferno/loss_fns/variational_free_energy.py
inferno/loss_fns/wrapped_torch_loss_fns.py
inferno/models/__init__.py
inferno/models/ensemble.py
inferno/models/lenet5.py
inferno/models/mlp.py
inferno/models/resnet.py
inferno_torch-0.0.8.dist-info/licenses/LICENSE
inferno_torch-0.0.8.dist-info/METADATA
inferno_torch-0.0.8.dist-info/WHEEL
inferno_torch-0.0.8.dist-info/top_level.txt
inferno_torch-0.0.8.dist-info/RECORD
